{"Hard Venom-VR15":1,"Hard Venom-epic rock music 2":1,"Hard Venom-VR13-mp3master":1,"Hard Venom-vr12 remaster":1,"Hard Venom-Epic Battle Remaster":1,"Hard Venom-vr10 remaster":1,"Hard Venom-vr9 remaster":1,"Hard Venom-bm5 remaster":1,"Hard Venom-bm7 remaster":1,"Hard Venom-BM4 Remaster":1,"Hard Venom-BM2 Remaster":1,"Hard Venom-bm3 remaster":1,"Hard Venom-bm6 remaster":1,"Hard Venom-Vampire Rising Remaster":1,"Hard Venom-Intro":1,"モーニング娘。-まじですかスカ!":1,"モーニング娘。-OK YEAH!":1,"モーニング娘。-乙女のタイミング":1,"モーニング娘。-My Way〜女子校花道〜":1,"モーニング娘。-彼と一緒にお店がしたい!":1,"モーニング娘。-この地球の平和を本気で願ってるんだよ!":1,"モーニング娘。-この愛を重ねて":1,"モーニング娘。-怪傑ポジティブA":1,"モーニング娘。-好きだな君が":1,"モーニング娘。-シルバーの腕時計":1,"モーニング娘。-Only you":1,"モーニング娘。-Give me 愛":1,"Opeth-The Apostle in Triumph":1,"Opeth-Requiem":1,"Opeth-The Twilight Is My Robe":1,"Opeth-Forest of October":1,"Opeth-Silhouette":1,"Opeth-Under the Weeping Moon":1,"Opeth-In Mist She Was Standing":1,"Opeth-Master's Apprentices":1,"Opeth-For Absent Friends":1,"Opeth-A Fair Judgement":1,"Opeth-Deliverance":1,"Opeth-Wreath":1,"PassCode-Link":1,"PassCode-Seize the day!!":1,"PassCode-アスタリスク":1,"PassCode-over there":1,"PassCode-Let the revelry begin":1,"PassCode-XYZ":1,"PassCode-Club Kids Never Die":1,"PassCode-Kissの花束":1,"PassCode-激動プログレッシブ":1,"PassCode-Toxic":1,"偶想Drop-ド田舎PUNK擬女":1,"偶想Drop-Level6":1,"偶想Drop-反抗期熊さんボコボコparadise!!":1,"偶想Drop-slow RAIN@東京":1,"偶想Drop-別に上手じゃなくていいじゃん、たかが音楽なんだから。ねぇ?…刺女△":1,"偶想Drop-Level":1,"偶想Drop-暴走少女":1,"偶想Drop-No.18":2,"偶想Drop-I do!I do!":2,"偶想Drop-ひらり、ひらひら":2,"偶想Drop-偶想Drop":2,"World's End Girlfriend-unfinished finale shed":1,"World's End Girlfriend-The Offering Inferno":1,"World's End Girlfriend-Der Spiegel im Spiegel im Spiegel":1,"World's End Girlfriend-Bohemian Purgatory Part.3":1,"World's End Girlfriend-Bohemian Purgatory Part.2":1,"World's End Girlfriend-Bohemian Purgatory Part.1":1,"World's End Girlfriend-GALAXY KID 666":1,"World's End Girlfriend-Helter Skelter Cha-Cha-Cha":1,"World's End Girlfriend-ULYSSES GAZER":1,"World's End Girlfriend-DECALOGUE minus 8":1,"World's End Girlfriend-Teen Age Ziggy":1,"World's End Girlfriend-Les Enfants du Paradis":1,"World's End Girlfriend-The Divine Comedy Reverse":1,"NEXT少女事件-adolescence":1,"NEXT少女事件-SETSUNA NEXT":1,"NEXT少女事件-Screaming idol":1,"Haken-Bound By Gravity":1,"Haken-The Endless Knot":1,"Haken-Red Giant":1,"Haken-Earthrise":1,"Haken-The Architect":1,"Haken-Lapse":1,"Haken-1985":1,"Haken-Initiate":1,"Haken-affinity.exe":1,"Cryptopsy-Endless Cemetery":1,"Cryptopsy-The End":1,"Cryptopsy-The Pestilence That Walketh in Darkness (Psalm 91: 5-8)":1,"Cryptopsy-Angelskingarden":1,"Cryptopsy-Keeping The Cadaver Dogs Busy":1,"Cryptopsy-The Frantic Pace Of Dying":1,"Cryptopsy-The Curse Of The Great":1,"Cryptopsy-Adeste Infidelis":1,"Cryptopsy-Carrionshine":1,"Cryptopsy-In The Kingdom Where Everything Dies, The Sky Is Mortal":1,"Cryptopsy-Luminum":1,"2&-ポッピングシャワーの雨":1,"2&-リアル":1,"2&-ドリーム":1,"2&-○の理論":1,"2&-未来を":1,"2&-兎と奴隷とカシオペア":1,"2&-ネガポジmonster":1,"2&-限界圧縮人形":1,"2&-片目のLiliy":1,"The Meads of Asphodel-A Canticle for the lost amputees of Aelia Capitolina who have been trampled under the iron shod hooves of salivating Hell Rams and impaled on the shimmering tusks of salvation within the abandoned tabernacle of a Bronze Age myth":1,"The Meads of Asphodel-Apostle Of The Uncircumcised":1,"The Meads of Asphodel-From Eagle To Cross":1,"The Meads of Asphodel-Genesis Of Death":1,"The Meads of Asphodel-Jew Killer":1,"The Meads of Asphodel-Dark Gethsemane":1,"The Meads of Asphodel-Man From Kerioth":1,"The Meads of Asphodel-Stiller Of Tempests":1,"The Meads of Asphodel-Addicted To God":1,"The Meads of Asphodel-Apocalypse Of Lazarus":1,"The Meads of Asphodel-My Psychotic Sand Deity":1,"The Meads of Asphodel-Boiled In Hell Broth And Grave Dust (Intro)":1,"Lykathea Aflame-Walking in the Garden of Ma'at":1,"Lykathea Aflame-An Old Man and a Child":1,"Lykathea Aflame-A Step Closer":1,"Lykathea Aflame-Sadness and Strength":1,"Lykathea Aflame-Shine of Consolation":1,"Lykathea Aflame-On the Way Home":1,"Lykathea Aflame-To Give":1,"Lykathea Aflame-Flowering Entities":1,"Lykathea Aflame-Bringer of Elvenefris Flame":1,"Lykathea Aflame-To Become Shelter and Salvation":1,"Lykathea Aflame-Land Where Sympathy Is Air":1,"Koto-シンデレラ症候群":1,"Koto-プラトニックプラネット":1,"Koto-SixteenSick":1,"Koto-バレンタインズバレリーナ":1,"Koto-エンジェルがエンドレス":1,"Koto-推定スウィーティ":1,"Koto-くえすちょん くえすと":1,"Koto-パステルパスポート":1,"Diablo Swing Orchestra-Justice For Saint Mary":2,"Diablo Swing Orchestra-Of Kali Ma Calibre":2,"Diablo Swing Orchestra-Honey Trap Aftermath":2,"Diablo Swing Orchestra-Mass Rapture":2,"Diablo Swing Orchestra-Aurora":2,"Diablo Swing Orchestra-Exit Strategy of a Wrecking Ball":2,"Diablo Swing Orchestra-Black Box Messiah":2,"Diablo Swing Orchestra-How To Organize a Lynch Mob":2,"Diablo Swing Orchestra-Kevlar Sweethearts":2,"Diablo Swing Orchestra-Guerrilla Laments":2,"Diablo Swing Orchestra-Voodoo Mon Amour":2,"Diablo Swing Orchestra-Pink Noise Waltz":1,"Diablo Swing Orchestra-Porcelain Judas":1,"Diablo Swing Orchestra-Zodiac Virtues":1,"Diablo Swing Orchestra-Qualms Of Conscience":1,"Diablo Swing Orchestra-Wedding March For a Bullet":1,"Diablo Swing Orchestra-Infralove":1,"Diablo Swing Orchestra-Gunpowder Chant":1,"Diablo Swing Orchestra-Velvet Embracer":1,"Diablo Swing Orchestra-D'angelo":1,"Diablo Swing Orchestra-Rag Doll Physics":1,"Diablo Swing Orchestra-Poetic Pitbull Revolutions":1,"Diablo Swing Orchestra-Heroines":1,"Diablo Swing Orchestra-Balrog Boogie":1,"Muse-Megalomania":1,"Muse-Feeling Good":1,"Muse-Darkshines":1,"Muse-Screenager":1,"Muse-Micro Cuts":1,"Muse-Citizen Erased":1,"Muse-Plug In Baby":1,"Muse-Hyper Music":1,"Muse-Space Dementia":1,"Muse-Bliss":1,"Muse-New Born":1,"Mors Principium Est-No More":2,"Mors Principium Est-Blood of Heroes":2,"Mors Principium Est-The Glass Womb":2,"Mors Principium Est-Pressure":2,"Mors Principium Est-Fragile Flesh":2,"Mors Principium Est-The Unborn":2,"Mors Principium Est-Spirit-conception":2,"Mors Principium Est-Altered State Of Consciousness":2,"Mors Principium Est-Two Steps Away":2,"Mors Principium Est-Parasites Of Paradise":2,"Mors Principium Est-The Harmony Remains":2,"Mors Principium Est-Pure":2,"Hard Venom-Ice":1,"Hard Venom-Water":1,"Hard Venom-Fire":1,"Hard Venom-Air":1,"Hard Venom-The Agonising Screams of Torture":1,"Hard Venom-Brudt Stilhed":1,"Hard Venom-Adriatic Splendour":1,"Hard Venom-The Forgotten Winter":1,"Hard Venom-Apocalypse":1,"Hard Venom-My Vice is Sacrifice":1,"Hard Venom-Black Hordes of Fallen Angels":1,"Hard Venom-The Beast":1,"Hard Venom-Prelude to a Mass Murder":1,"Kvelertak-Kvelertak":1,"Kvelertak-Tordenbrak":1,"Kvelertak-Undertro":1,"Kvelertak-Nekrokosmos":1,"Kvelertak-Månelyst":1,"Kvelertak-Snilepisk":1,"Kvelertak-Evig vandrar":1,"Kvelertak-Bruane brenn":1,"Kvelertak-Trepan":1,"Kvelertak-Spring fra livet":1,"Kvelertak-Åpenbaring":1,"Buono!-We are Buono!～Buono!のテーマ":1,"Buono!-タビダチの歌":1,"Buono!-紅茶の美味しい店":1,"Buono!-Blue-Sky-Blue":1,"Buono!-カタオモイ。":1,"Buono!-Ｂｒａｖｏ☆Ｂｒａｖｏ（テレビ東京系番組「しゅごキャラ！パーティー！」エンディングテーマ）":1,"Buono!-Take It Easy!":1,"Buono!-うらはら":1,"Buono!-MY BOY":1,"Buono!-Ｉｎｄｅｐｅｎｄｅｎｔ　Ｇｉｒｌ～独立女子であるために":1,"Buono!-Our Songs":1,"Buono!-One Way = My Way":1}